restreamsolutions/__init__.py
restreamsolutions/base_interface.py
restreamsolutions/base_pad_site.py
restreamsolutions/communicator.py
restreamsolutions/constants.py
restreamsolutions/data_changes.py
restreamsolutions/data_object.py
restreamsolutions/exceptions.py
restreamsolutions/pad.py
restreamsolutions/site.py
restreamsolutions/state.py
restreamsolutions/utils/singleton.py
restreamsolutions-0.3.0.dist-info/licenses/LICENSE
restreamsolutions-0.3.0.dist-info/METADATA
restreamsolutions-0.3.0.dist-info/WHEEL
restreamsolutions-0.3.0.dist-info/RECORD
