Metadata-Version: 2.4
Name: restreamsolutions
Version: 0.3.0
Summary: ReStream Datastore SDK
License-Expression: MIT
License-File: LICENSE
Keywords: datastore,sdk,restreamsolutions,api
Author: Riley Seaman
Author-email: rseaman@restreamsolutions.com
Requires-Python: >=3.10,<4.0
Classifier: Intended Audience :: Developers
Classifier: License :: OSI Approved :: MIT License
Classifier: Programming Language :: Python
Classifier: Programming Language :: Python :: 3
Classifier: Programming Language :: Python :: 3 :: Only
Classifier: Programming Language :: Python :: 3.10
Classifier: Programming Language :: Python :: 3.11
Classifier: Programming Language :: Python :: 3.12
Classifier: Programming Language :: Python :: 3.13
Classifier: Topic :: Software Development :: Libraries
Classifier: Topic :: Internet :: WWW/HTTP
Requires-Dist: aiofiles (>=24.1.0)
Requires-Dist: aiohttp (>=3.13.1)
Requires-Dist: httpx (>=0.27.0)
Requires-Dist: ijson (>=3.4.0)
Requires-Dist: pandas (>=2.0.0)
Requires-Dist: python-dateutil (>=2.9.0)
Requires-Dist: requests (>=2.0.0)
Requires-Dist: websocket-client (>=1.8.0)
Project-URL: Changelog, https://github.com/ReStream-Solutions/restreamsolutions/blob/main/CHANGELOG.md
Project-URL: Homepage, https://restreamsolutions.com/
Project-URL: Repository, https://github.com/ReStream-Solutions/restreamsolutions
